{
    "description": "",
    "tags": [
        {
            "id": 20436169,
            "tagId": 31789,
            "name": "sequence",
            "value": "M0603",
            "labelerLogin": "inbox@datasetninja.com",
            "createdAt": "2024-03-05T11:48:03.434Z",
            "updatedAt": "2024-03-05T11:48:03.434Z"
        },
        {
            "id": 20436170,
            "tagId": 31798,
            "name": "daylight",
            "value": null,
            "labelerLogin": "inbox@datasetninja.com",
            "createdAt": "2024-03-05T11:48:03.434Z",
            "updatedAt": "2024-03-05T11:48:03.434Z"
        },
        {
            "id": 20436171,
            "tagId": 31802,
            "name": "medium alt",
            "value": null,
            "labelerLogin": "inbox@datasetninja.com",
            "createdAt": "2024-03-05T11:48:03.434Z",
            "updatedAt": "2024-03-05T11:48:03.434Z"
        },
        {
            "id": 20436172,
            "tagId": 31806,
            "name": "bird view",
            "value": null,
            "labelerLogin": "inbox@datasetninja.com",
            "createdAt": "2024-03-05T11:48:03.434Z",
            "updatedAt": "2024-03-05T11:48:03.434Z"
        },
        {
            "id": 20436173,
            "tagId": 31807,
            "name": "long term",
            "value": null,
            "labelerLogin": "inbox@datasetninja.com",
            "createdAt": "2024-03-05T11:48:03.434Z",
            "updatedAt": "2024-03-05T11:48:03.434Z"
        }
    ],
    "size": {
        "height": 540,
        "width": 1024
    },
    "objects": [
        {
            "id": 151311374,
            "classId": 6544594,
            "objectId": null,
            "description": "",
            "geometryType": "rectangle",
            "labelerLogin": "inbox@datasetninja.com",
            "createdAt": "2024-03-05T11:48:03.435Z",
            "updatedAt": "2024-03-05T11:48:03.435Z",
            "tags": [
                {
                    "id": 109848438,
                    "tagId": 31790,
                    "name": "target id",
                    "value": 1,
                    "labelerLogin": "inbox@datasetninja.com",
                    "createdAt": "2024-03-05T11:48:03.435Z",
                    "updatedAt": "2024-03-05T11:48:03.435Z"
                },
                {
                    "id": 109848439,
                    "tagId": 31791,
                    "name": "no out",
                    "value": null,
                    "labelerLogin": "inbox@datasetninja.com",
                    "createdAt": "2024-03-05T11:48:03.435Z",
                    "updatedAt": "2024-03-05T11:48:03.435Z"
                },
                {
                    "id": 109848440,
                    "tagId": 31794,
                    "name": "no occlusion",
                    "value": null,
                    "labelerLogin": "inbox@datasetninja.com",
                    "createdAt": "2024-03-05T11:48:03.435Z",
                    "updatedAt": "2024-03-05T11:48:03.435Z"
                }
            ],
            "classTitle": "car",
            "points": {
                "exterior": [
                    [
                        442,
                        314
                    ],
                    [
                        466,
                        362
                    ]
                ],
                "interior": []
            }
        },
        {
            "id": 151311375,
            "classId": 6544594,
            "objectId": null,
            "description": "",
            "geometryType": "rectangle",
            "labelerLogin": "inbox@datasetninja.com",
            "createdAt": "2024-03-05T11:48:03.436Z",
            "updatedAt": "2024-03-05T11:48:03.436Z",
            "tags": [
                {
                    "id": 109848441,
                    "tagId": 31790,
                    "name": "target id",
                    "value": 4,
                    "labelerLogin": "inbox@datasetninja.com",
                    "createdAt": "2024-03-05T11:48:03.436Z",
                    "updatedAt": "2024-03-05T11:48:03.436Z"
                },
                {
                    "id": 109848442,
                    "tagId": 31791,
                    "name": "no out",
                    "value": null,
                    "labelerLogin": "inbox@datasetninja.com",
                    "createdAt": "2024-03-05T11:48:03.436Z",
                    "updatedAt": "2024-03-05T11:48:03.436Z"
                },
                {
                    "id": 109848443,
                    "tagId": 31794,
                    "name": "no occlusion",
                    "value": null,
                    "labelerLogin": "inbox@datasetninja.com",
                    "createdAt": "2024-03-05T11:48:03.436Z",
                    "updatedAt": "2024-03-05T11:48:03.436Z"
                }
            ],
            "classTitle": "car",
            "points": {
                "exterior": [
                    [
                        528,
                        149
                    ],
                    [
                        552,
                        189
                    ]
                ],
                "interior": []
            }
        },
        {
            "id": 151311376,
            "classId": 6544595,
            "objectId": null,
            "description": "",
            "geometryType": "rectangle",
            "labelerLogin": "inbox@datasetninja.com",
            "createdAt": "2024-03-05T11:48:03.443Z",
            "updatedAt": "2024-03-05T11:48:03.443Z",
            "tags": [
                {
                    "id": 109848444,
                    "tagId": 31790,
                    "name": "target id",
                    "value": 5,
                    "labelerLogin": "inbox@datasetninja.com",
                    "createdAt": "2024-03-05T11:48:03.437Z",
                    "updatedAt": "2024-03-05T11:48:03.437Z"
                },
                {
                    "id": 109848445,
                    "tagId": 31791,
                    "name": "no out",
                    "value": null,
                    "labelerLogin": "inbox@datasetninja.com",
                    "createdAt": "2024-03-05T11:48:03.437Z",
                    "updatedAt": "2024-03-05T11:48:03.437Z"
                },
                {
                    "id": 109848446,
                    "tagId": 31794,
                    "name": "no occlusion",
                    "value": null,
                    "labelerLogin": "inbox@datasetninja.com",
                    "createdAt": "2024-03-05T11:48:03.437Z",
                    "updatedAt": "2024-03-05T11:48:03.437Z"
                }
            ],
            "classTitle": "truck",
            "points": {
                "exterior": [
                    [
                        349,
                        431
                    ],
                    [
                        384,
                        499
                    ]
                ],
                "interior": []
            }
        },
        {
            "id": 151311377,
            "classId": 6544594,
            "objectId": null,
            "description": "",
            "geometryType": "rectangle",
            "labelerLogin": "inbox@datasetninja.com",
            "createdAt": "2024-03-05T11:48:03.444Z",
            "updatedAt": "2024-03-05T11:48:03.444Z",
            "tags": [
                {
                    "id": 109848447,
                    "tagId": 31790,
                    "name": "target id",
                    "value": 6,
                    "labelerLogin": "inbox@datasetninja.com",
                    "createdAt": "2024-03-05T11:48:03.444Z",
                    "updatedAt": "2024-03-05T11:48:03.444Z"
                },
                {
                    "id": 109848448,
                    "tagId": 31791,
                    "name": "no out",
                    "value": null,
                    "labelerLogin": "inbox@datasetninja.com",
                    "createdAt": "2024-03-05T11:48:03.444Z",
                    "updatedAt": "2024-03-05T11:48:03.444Z"
                },
                {
                    "id": 109848449,
                    "tagId": 31794,
                    "name": "no occlusion",
                    "value": null,
                    "labelerLogin": "inbox@datasetninja.com",
                    "createdAt": "2024-03-05T11:48:03.444Z",
                    "updatedAt": "2024-03-05T11:48:03.444Z"
                }
            ],
            "classTitle": "car",
            "points": {
                "exterior": [
                    [
                        590,
                        169
                    ],
                    [
                        614,
                        218
                    ]
                ],
                "interior": []
            }
        },
        {
            "id": 151311378,
            "classId": 6544596,
            "objectId": null,
            "description": "",
            "geometryType": "rectangle",
            "labelerLogin": "inbox@datasetninja.com",
            "createdAt": "2024-03-05T11:48:03.444Z",
            "updatedAt": "2024-03-05T11:48:03.444Z",
            "tags": [
                {
                    "id": 109848450,
                    "tagId": 31790,
                    "name": "target id",
                    "value": 7,
                    "labelerLogin": "inbox@datasetninja.com",
                    "createdAt": "2024-03-05T11:48:03.444Z",
                    "updatedAt": "2024-03-05T11:48:03.444Z"
                },
                {
                    "id": 109848451,
                    "tagId": 31791,
                    "name": "no out",
                    "value": null,
                    "labelerLogin": "inbox@datasetninja.com",
                    "createdAt": "2024-03-05T11:48:03.444Z",
                    "updatedAt": "2024-03-05T11:48:03.444Z"
                },
                {
                    "id": 109848452,
                    "tagId": 31794,
                    "name": "no occlusion",
                    "value": null,
                    "labelerLogin": "inbox@datasetninja.com",
                    "createdAt": "2024-03-05T11:48:03.444Z",
                    "updatedAt": "2024-03-05T11:48:03.444Z"
                }
            ],
            "classTitle": "bus",
            "points": {
                "exterior": [
                    [
                        361,
                        222
                    ],
                    [
                        400,
                        351
                    ]
                ],
                "interior": []
            }
        },
        {
            "id": 151311379,
            "classId": 6544594,
            "objectId": null,
            "description": "",
            "geometryType": "rectangle",
            "labelerLogin": "inbox@datasetninja.com",
            "createdAt": "2024-03-05T11:48:03.445Z",
            "updatedAt": "2024-03-05T11:48:03.445Z",
            "tags": [
                {
                    "id": 109848453,
                    "tagId": 31790,
                    "name": "target id",
                    "value": 8,
                    "labelerLogin": "inbox@datasetninja.com",
                    "createdAt": "2024-03-05T11:48:03.445Z",
                    "updatedAt": "2024-03-05T11:48:03.445Z"
                },
                {
                    "id": 109848454,
                    "tagId": 31791,
                    "name": "no out",
                    "value": null,
                    "labelerLogin": "inbox@datasetninja.com",
                    "createdAt": "2024-03-05T11:48:03.445Z",
                    "updatedAt": "2024-03-05T11:48:03.445Z"
                },
                {
                    "id": 109848455,
                    "tagId": 31794,
                    "name": "no occlusion",
                    "value": null,
                    "labelerLogin": "inbox@datasetninja.com",
                    "createdAt": "2024-03-05T11:48:03.445Z",
                    "updatedAt": "2024-03-05T11:48:03.445Z"
                }
            ],
            "classTitle": "car",
            "points": {
                "exterior": [
                    [
                        413,
                        279
                    ],
                    [
                        437,
                        328
                    ]
                ],
                "interior": []
            }
        },
        {
            "id": 151311380,
            "classId": 6544594,
            "objectId": null,
            "description": "",
            "geometryType": "rectangle",
            "labelerLogin": "inbox@datasetninja.com",
            "createdAt": "2024-03-05T11:48:03.446Z",
            "updatedAt": "2024-03-05T11:48:03.446Z",
            "tags": [
                {
                    "id": 109848456,
                    "tagId": 31790,
                    "name": "target id",
                    "value": 9,
                    "labelerLogin": "inbox@datasetninja.com",
                    "createdAt": "2024-03-05T11:48:03.446Z",
                    "updatedAt": "2024-03-05T11:48:03.446Z"
                },
                {
                    "id": 109848457,
                    "tagId": 31793,
                    "name": "small out",
                    "value": null,
                    "labelerLogin": "inbox@datasetninja.com",
                    "createdAt": "2024-03-05T11:48:03.446Z",
                    "updatedAt": "2024-03-05T11:48:03.446Z"
                },
                {
                    "id": 109848458,
                    "tagId": 31794,
                    "name": "no occlusion",
                    "value": null,
                    "labelerLogin": "inbox@datasetninja.com",
                    "createdAt": "2024-03-05T11:48:03.446Z",
                    "updatedAt": "2024-03-05T11:48:03.446Z"
                }
            ],
            "classTitle": "car",
            "points": {
                "exterior": [
                    [
                        450,
                        112
                    ],
                    [
                        474,
                        161
                    ]
                ],
                "interior": []
            }
        },
        {
            "id": 151311381,
            "classId": 6544594,
            "objectId": null,
            "description": "",
            "geometryType": "rectangle",
            "labelerLogin": "inbox@datasetninja.com",
            "createdAt": "2024-03-05T11:48:03.446Z",
            "updatedAt": "2024-03-05T11:48:03.446Z",
            "tags": [
                {
                    "id": 109848459,
                    "tagId": 31790,
                    "name": "target id",
                    "value": 10,
                    "labelerLogin": "inbox@datasetninja.com",
                    "createdAt": "2024-03-05T11:48:03.446Z",
                    "updatedAt": "2024-03-05T11:48:03.446Z"
                },
                {
                    "id": 109848460,
                    "tagId": 31791,
                    "name": "no out",
                    "value": null,
                    "labelerLogin": "inbox@datasetninja.com",
                    "createdAt": "2024-03-05T11:48:03.446Z",
                    "updatedAt": "2024-03-05T11:48:03.446Z"
                },
                {
                    "id": 109848461,
                    "tagId": 31794,
                    "name": "no occlusion",
                    "value": null,
                    "labelerLogin": "inbox@datasetninja.com",
                    "createdAt": "2024-03-05T11:48:03.446Z",
                    "updatedAt": "2024-03-05T11:48:03.446Z"
                }
            ],
            "classTitle": "car",
            "points": {
                "exterior": [
                    [
                        410,
                        139
                    ],
                    [
                        433,
                        187
                    ]
                ],
                "interior": []
            }
        },
        {
            "id": 151311382,
            "classId": 6544594,
            "objectId": null,
            "description": "",
            "geometryType": "rectangle",
            "labelerLogin": "inbox@datasetninja.com",
            "createdAt": "2024-03-05T11:48:03.447Z",
            "updatedAt": "2024-03-05T11:48:03.447Z",
            "tags": [
                {
                    "id": 109848462,
                    "tagId": 31790,
                    "name": "target id",
                    "value": 11,
                    "labelerLogin": "inbox@datasetninja.com",
                    "createdAt": "2024-03-05T11:48:03.447Z",
                    "updatedAt": "2024-03-05T11:48:03.447Z"
                },
                {
                    "id": 109848463,
                    "tagId": 31791,
                    "name": "no out",
                    "value": null,
                    "labelerLogin": "inbox@datasetninja.com",
                    "createdAt": "2024-03-05T11:48:03.447Z",
                    "updatedAt": "2024-03-05T11:48:03.447Z"
                },
                {
                    "id": 109848464,
                    "tagId": 31794,
                    "name": "no occlusion",
                    "value": null,
                    "labelerLogin": "inbox@datasetninja.com",
                    "createdAt": "2024-03-05T11:48:03.447Z",
                    "updatedAt": "2024-03-05T11:48:03.447Z"
                }
            ],
            "classTitle": "car",
            "points": {
                "exterior": [
                    [
                        383,
                        134
                    ],
                    [
                        404,
                        172
                    ]
                ],
                "interior": []
            }
        },
        {
            "id": 151311383,
            "classId": 6544594,
            "objectId": null,
            "description": "",
            "geometryType": "rectangle",
            "labelerLogin": "inbox@datasetninja.com",
            "createdAt": "2024-03-05T11:48:03.448Z",
            "updatedAt": "2024-03-05T11:48:03.448Z",
            "tags": [
                {
                    "id": 109848465,
                    "tagId": 31790,
                    "name": "target id",
                    "value": 12,
                    "labelerLogin": "inbox@datasetninja.com",
                    "createdAt": "2024-03-05T11:48:03.448Z",
                    "updatedAt": "2024-03-05T11:48:03.448Z"
                },
                {
                    "id": 109848466,
                    "tagId": 31791,
                    "name": "no out",
                    "value": null,
                    "labelerLogin": "inbox@datasetninja.com",
                    "createdAt": "2024-03-05T11:48:03.448Z",
                    "updatedAt": "2024-03-05T11:48:03.448Z"
                },
                {
                    "id": 109848467,
                    "tagId": 31794,
                    "name": "no occlusion",
                    "value": null,
                    "labelerLogin": "inbox@datasetninja.com",
                    "createdAt": "2024-03-05T11:48:03.448Z",
                    "updatedAt": "2024-03-05T11:48:03.448Z"
                }
            ],
            "classTitle": "car",
            "points": {
                "exterior": [
                    [
                        380,
                        43
                    ],
                    [
                        401,
                        96
                    ]
                ],
                "interior": []
            }
        },
        {
            "id": 151311384,
            "classId": 6544596,
            "objectId": null,
            "description": "",
            "geometryType": "rectangle",
            "labelerLogin": "inbox@datasetninja.com",
            "createdAt": "2024-03-05T11:48:03.449Z",
            "updatedAt": "2024-03-05T11:48:03.449Z",
            "tags": [
                {
                    "id": 109848468,
                    "tagId": 31790,
                    "name": "target id",
                    "value": 13,
                    "labelerLogin": "inbox@datasetninja.com",
                    "createdAt": "2024-03-05T11:48:03.449Z",
                    "updatedAt": "2024-03-05T11:48:03.449Z"
                },
                {
                    "id": 109848469,
                    "tagId": 31791,
                    "name": "no out",
                    "value": null,
                    "labelerLogin": "inbox@datasetninja.com",
                    "createdAt": "2024-03-05T11:48:03.449Z",
                    "updatedAt": "2024-03-05T11:48:03.449Z"
                },
                {
                    "id": 109848470,
                    "tagId": 31794,
                    "name": "no occlusion",
                    "value": null,
                    "labelerLogin": "inbox@datasetninja.com",
                    "createdAt": "2024-03-05T11:48:03.449Z",
                    "updatedAt": "2024-03-05T11:48:03.449Z"
                }
            ],
            "classTitle": "bus",
            "points": {
                "exterior": [
                    [
                        685,
                        251
                    ],
                    [
                        795,
                        339
                    ]
                ],
                "interior": []
            }
        },
        {
            "id": 151311385,
            "classId": 6544594,
            "objectId": null,
            "description": "",
            "geometryType": "rectangle",
            "labelerLogin": "inbox@datasetninja.com",
            "createdAt": "2024-03-05T11:48:03.450Z",
            "updatedAt": "2024-03-05T11:48:03.450Z",
            "tags": [
                {
                    "id": 109848471,
                    "tagId": 31790,
                    "name": "target id",
                    "value": 14,
                    "labelerLogin": "inbox@datasetninja.com",
                    "createdAt": "2024-03-05T11:48:03.450Z",
                    "updatedAt": "2024-03-05T11:48:03.450Z"
                },
                {
                    "id": 109848472,
                    "tagId": 31791,
                    "name": "no out",
                    "value": null,
                    "labelerLogin": "inbox@datasetninja.com",
                    "createdAt": "2024-03-05T11:48:03.450Z",
                    "updatedAt": "2024-03-05T11:48:03.450Z"
                },
                {
                    "id": 109848473,
                    "tagId": 31794,
                    "name": "no occlusion",
                    "value": null,
                    "labelerLogin": "inbox@datasetninja.com",
                    "createdAt": "2024-03-05T11:48:03.450Z",
                    "updatedAt": "2024-03-05T11:48:03.450Z"
                }
            ],
            "classTitle": "car",
            "points": {
                "exterior": [
                    [
                        555,
                        231
                    ],
                    [
                        578,
                        279
                    ]
                ],
                "interior": []
            }
        },
        {
            "id": 151311386,
            "classId": 6544594,
            "objectId": null,
            "description": "",
            "geometryType": "rectangle",
            "labelerLogin": "inbox@datasetninja.com",
            "createdAt": "2024-03-05T11:48:03.451Z",
            "updatedAt": "2024-03-05T11:48:03.451Z",
            "tags": [
                {
                    "id": 109848474,
                    "tagId": 31790,
                    "name": "target id",
                    "value": 15,
                    "labelerLogin": "inbox@datasetninja.com",
                    "createdAt": "2024-03-05T11:48:03.451Z",
                    "updatedAt": "2024-03-05T11:48:03.451Z"
                },
                {
                    "id": 109848475,
                    "tagId": 31791,
                    "name": "no out",
                    "value": null,
                    "labelerLogin": "inbox@datasetninja.com",
                    "createdAt": "2024-03-05T11:48:03.451Z",
                    "updatedAt": "2024-03-05T11:48:03.451Z"
                },
                {
                    "id": 109848476,
                    "tagId": 31794,
                    "name": "no occlusion",
                    "value": null,
                    "labelerLogin": "inbox@datasetninja.com",
                    "createdAt": "2024-03-05T11:48:03.451Z",
                    "updatedAt": "2024-03-05T11:48:03.451Z"
                }
            ],
            "classTitle": "car",
            "points": {
                "exterior": [
                    [
                        590,
                        323
                    ],
                    [
                        614,
                        375
                    ]
                ],
                "interior": []
            }
        },
        {
            "id": 151311387,
            "classId": 6544594,
            "objectId": null,
            "description": "",
            "geometryType": "rectangle",
            "labelerLogin": "inbox@datasetninja.com",
            "createdAt": "2024-03-05T11:48:03.452Z",
            "updatedAt": "2024-03-05T11:48:03.452Z",
            "tags": [
                {
                    "id": 109848477,
                    "tagId": 31790,
                    "name": "target id",
                    "value": 16,
                    "labelerLogin": "inbox@datasetninja.com",
                    "createdAt": "2024-03-05T11:48:03.452Z",
                    "updatedAt": "2024-03-05T11:48:03.452Z"
                },
                {
                    "id": 109848478,
                    "tagId": 31791,
                    "name": "no out",
                    "value": null,
                    "labelerLogin": "inbox@datasetninja.com",
                    "createdAt": "2024-03-05T11:48:03.452Z",
                    "updatedAt": "2024-03-05T11:48:03.452Z"
                },
                {
                    "id": 109848479,
                    "tagId": 31794,
                    "name": "no occlusion",
                    "value": null,
                    "labelerLogin": "inbox@datasetninja.com",
                    "createdAt": "2024-03-05T11:48:03.452Z",
                    "updatedAt": "2024-03-05T11:48:03.452Z"
                }
            ],
            "classTitle": "car",
            "points": {
                "exterior": [
                    [
                        555,
                        345
                    ],
                    [
                        579,
                        392
                    ]
                ],
                "interior": []
            }
        },
        {
            "id": 151311388,
            "classId": 6544594,
            "objectId": null,
            "description": "",
            "geometryType": "rectangle",
            "labelerLogin": "inbox@datasetninja.com",
            "createdAt": "2024-03-05T11:48:03.453Z",
            "updatedAt": "2024-03-05T11:48:03.453Z",
            "tags": [
                {
                    "id": 109848480,
                    "tagId": 31790,
                    "name": "target id",
                    "value": 17,
                    "labelerLogin": "inbox@datasetninja.com",
                    "createdAt": "2024-03-05T11:48:03.453Z",
                    "updatedAt": "2024-03-05T11:48:03.453Z"
                },
                {
                    "id": 109848481,
                    "tagId": 31791,
                    "name": "no out",
                    "value": null,
                    "labelerLogin": "inbox@datasetninja.com",
                    "createdAt": "2024-03-05T11:48:03.453Z",
                    "updatedAt": "2024-03-05T11:48:03.453Z"
                },
                {
                    "id": 109848482,
                    "tagId": 31794,
                    "name": "no occlusion",
                    "value": null,
                    "labelerLogin": "inbox@datasetninja.com",
                    "createdAt": "2024-03-05T11:48:03.453Z",
                    "updatedAt": "2024-03-05T11:48:03.453Z"
                }
            ],
            "classTitle": "car",
            "points": {
                "exterior": [
                    [
                        587,
                        453
                    ],
                    [
                        610,
                        501
                    ]
                ],
                "interior": []
            }
        },
        {
            "id": 151311389,
            "classId": 6544594,
            "objectId": null,
            "description": "",
            "geometryType": "rectangle",
            "labelerLogin": "inbox@datasetninja.com",
            "createdAt": "2024-03-05T11:48:03.454Z",
            "updatedAt": "2024-03-05T11:48:03.454Z",
            "tags": [
                {
                    "id": 109848483,
                    "tagId": 31790,
                    "name": "target id",
                    "value": 19,
                    "labelerLogin": "inbox@datasetninja.com",
                    "createdAt": "2024-03-05T11:48:03.454Z",
                    "updatedAt": "2024-03-05T11:48:03.454Z"
                },
                {
                    "id": 109848484,
                    "tagId": 31793,
                    "name": "small out",
                    "value": null,
                    "labelerLogin": "inbox@datasetninja.com",
                    "createdAt": "2024-03-05T11:48:03.454Z",
                    "updatedAt": "2024-03-05T11:48:03.454Z"
                },
                {
                    "id": 109848485,
                    "tagId": 31794,
                    "name": "no occlusion",
                    "value": null,
                    "labelerLogin": "inbox@datasetninja.com",
                    "createdAt": "2024-03-05T11:48:03.454Z",
                    "updatedAt": "2024-03-05T11:48:03.454Z"
                }
            ],
            "classTitle": "car",
            "points": {
                "exterior": [
                    [
                        414,
                        0
                    ],
                    [
                        435,
                        44
                    ]
                ],
                "interior": []
            }
        },
        {
            "id": 151311390,
            "classId": 6544594,
            "objectId": null,
            "description": "",
            "geometryType": "rectangle",
            "labelerLogin": "inbox@datasetninja.com",
            "createdAt": "2024-03-05T11:48:03.455Z",
            "updatedAt": "2024-03-05T11:48:03.455Z",
            "tags": [
                {
                    "id": 109848486,
                    "tagId": 31790,
                    "name": "target id",
                    "value": 29,
                    "labelerLogin": "inbox@datasetninja.com",
                    "createdAt": "2024-03-05T11:48:03.455Z",
                    "updatedAt": "2024-03-05T11:48:03.455Z"
                },
                {
                    "id": 109848487,
                    "tagId": 31791,
                    "name": "no out",
                    "value": null,
                    "labelerLogin": "inbox@datasetninja.com",
                    "createdAt": "2024-03-05T11:48:03.455Z",
                    "updatedAt": "2024-03-05T11:48:03.455Z"
                },
                {
                    "id": 109848488,
                    "tagId": 31794,
                    "name": "no occlusion",
                    "value": null,
                    "labelerLogin": "inbox@datasetninja.com",
                    "createdAt": "2024-03-05T11:48:03.455Z",
                    "updatedAt": "2024-03-05T11:48:03.455Z"
                }
            ],
            "classTitle": "car",
            "points": {
                "exterior": [
                    [
                        635,
                        377
                    ],
                    [
                        665,
                        423
                    ]
                ],
                "interior": []
            }
        },
        {
            "id": 151311391,
            "classId": 6544594,
            "objectId": null,
            "description": "",
            "geometryType": "rectangle",
            "labelerLogin": "inbox@datasetninja.com",
            "createdAt": "2024-03-05T11:48:03.456Z",
            "updatedAt": "2024-03-05T11:48:03.456Z",
            "tags": [
                {
                    "id": 109848489,
                    "tagId": 31790,
                    "name": "target id",
                    "value": 30,
                    "labelerLogin": "inbox@datasetninja.com",
                    "createdAt": "2024-03-05T11:48:03.456Z",
                    "updatedAt": "2024-03-05T11:48:03.456Z"
                },
                {
                    "id": 109848490,
                    "tagId": 31791,
                    "name": "no out",
                    "value": null,
                    "labelerLogin": "inbox@datasetninja.com",
                    "createdAt": "2024-03-05T11:48:03.456Z",
                    "updatedAt": "2024-03-05T11:48:03.456Z"
                },
                {
                    "id": 109848491,
                    "tagId": 31794,
                    "name": "no occlusion",
                    "value": null,
                    "labelerLogin": "inbox@datasetninja.com",
                    "createdAt": "2024-03-05T11:48:03.456Z",
                    "updatedAt": "2024-03-05T11:48:03.456Z"
                }
            ],
            "classTitle": "car",
            "points": {
                "exterior": [
                    [
                        625,
                        443
                    ],
                    [
                        650,
                        497
                    ]
                ],
                "interior": []
            }
        },
        {
            "id": 151311392,
            "classId": 6544594,
            "objectId": null,
            "description": "",
            "geometryType": "rectangle",
            "labelerLogin": "inbox@datasetninja.com",
            "createdAt": "2024-03-05T11:48:03.456Z",
            "updatedAt": "2024-03-05T11:48:03.456Z",
            "tags": [
                {
                    "id": 109848492,
                    "tagId": 31790,
                    "name": "target id",
                    "value": 40,
                    "labelerLogin": "inbox@datasetninja.com",
                    "createdAt": "2024-03-05T11:48:03.456Z",
                    "updatedAt": "2024-03-05T11:48:03.456Z"
                },
                {
                    "id": 109848493,
                    "tagId": 31791,
                    "name": "no out",
                    "value": null,
                    "labelerLogin": "inbox@datasetninja.com",
                    "createdAt": "2024-03-05T11:48:03.456Z",
                    "updatedAt": "2024-03-05T11:48:03.456Z"
                },
                {
                    "id": 109848494,
                    "tagId": 31794,
                    "name": "no occlusion",
                    "value": null,
                    "labelerLogin": "inbox@datasetninja.com",
                    "createdAt": "2024-03-05T11:48:03.456Z",
                    "updatedAt": "2024-03-05T11:48:03.456Z"
                }
            ],
            "classTitle": "car",
            "points": {
                "exterior": [
                    [
                        123,
                        338
                    ],
                    [
                        177,
                        360
                    ]
                ],
                "interior": []
            }
        },
        {
            "id": 151311393,
            "classId": 6544594,
            "objectId": null,
            "description": "",
            "geometryType": "rectangle",
            "labelerLogin": "inbox@datasetninja.com",
            "createdAt": "2024-03-05T11:48:03.457Z",
            "updatedAt": "2024-03-05T11:48:03.457Z",
            "tags": [
                {
                    "id": 109848495,
                    "tagId": 31790,
                    "name": "target id",
                    "value": 62,
                    "labelerLogin": "inbox@datasetninja.com",
                    "createdAt": "2024-03-05T11:48:03.457Z",
                    "updatedAt": "2024-03-05T11:48:03.457Z"
                },
                {
                    "id": 109848496,
                    "tagId": 31793,
                    "name": "small out",
                    "value": null,
                    "labelerLogin": "inbox@datasetninja.com",
                    "createdAt": "2024-03-05T11:48:03.457Z",
                    "updatedAt": "2024-03-05T11:48:03.457Z"
                },
                {
                    "id": 109848497,
                    "tagId": 31794,
                    "name": "no occlusion",
                    "value": null,
                    "labelerLogin": "inbox@datasetninja.com",
                    "createdAt": "2024-03-05T11:48:03.457Z",
                    "updatedAt": "2024-03-05T11:48:03.457Z"
                }
            ],
            "classTitle": "car",
            "points": {
                "exterior": [
                    [
                        487,
                        58
                    ],
                    [
                        507,
                        102
                    ]
                ],
                "interior": []
            }
        },
        {
            "id": 151311394,
            "classId": 6544594,
            "objectId": null,
            "description": "",
            "geometryType": "rectangle",
            "labelerLogin": "inbox@datasetninja.com",
            "createdAt": "2024-03-05T11:48:03.458Z",
            "updatedAt": "2024-03-05T11:48:03.458Z",
            "tags": [
                {
                    "id": 109848498,
                    "tagId": 31790,
                    "name": "target id",
                    "value": 63,
                    "labelerLogin": "inbox@datasetninja.com",
                    "createdAt": "2024-03-05T11:48:03.458Z",
                    "updatedAt": "2024-03-05T11:48:03.458Z"
                },
                {
                    "id": 109848499,
                    "tagId": 31791,
                    "name": "no out",
                    "value": null,
                    "labelerLogin": "inbox@datasetninja.com",
                    "createdAt": "2024-03-05T11:48:03.458Z",
                    "updatedAt": "2024-03-05T11:48:03.458Z"
                },
                {
                    "id": 109848500,
                    "tagId": 31794,
                    "name": "no occlusion",
                    "value": null,
                    "labelerLogin": "inbox@datasetninja.com",
                    "createdAt": "2024-03-05T11:48:03.458Z",
                    "updatedAt": "2024-03-05T11:48:03.458Z"
                }
            ],
            "classTitle": "car",
            "points": {
                "exterior": [
                    [
                        498,
                        138
                    ],
                    [
                        526,
                        182
                    ]
                ],
                "interior": []
            }
        },
        {
            "id": 151311395,
            "classId": 6544594,
            "objectId": null,
            "description": "",
            "geometryType": "rectangle",
            "labelerLogin": "inbox@datasetninja.com",
            "createdAt": "2024-03-05T11:48:03.458Z",
            "updatedAt": "2024-03-05T11:48:03.458Z",
            "tags": [
                {
                    "id": 109848501,
                    "tagId": 31790,
                    "name": "target id",
                    "value": 68,
                    "labelerLogin": "inbox@datasetninja.com",
                    "createdAt": "2024-03-05T11:48:03.458Z",
                    "updatedAt": "2024-03-05T11:48:03.458Z"
                },
                {
                    "id": 109848502,
                    "tagId": 31791,
                    "name": "no out",
                    "value": null,
                    "labelerLogin": "inbox@datasetninja.com",
                    "createdAt": "2024-03-05T11:48:03.458Z",
                    "updatedAt": "2024-03-05T11:48:03.458Z"
                },
                {
                    "id": 109848503,
                    "tagId": 31794,
                    "name": "no occlusion",
                    "value": null,
                    "labelerLogin": "inbox@datasetninja.com",
                    "createdAt": "2024-03-05T11:48:03.458Z",
                    "updatedAt": "2024-03-05T11:48:03.458Z"
                }
            ],
            "classTitle": "car",
            "points": {
                "exterior": [
                    [
                        503,
                        414
                    ],
                    [
                        527,
                        466
                    ]
                ],
                "interior": []
            }
        },
        {
            "id": 151311396,
            "classId": 6544594,
            "objectId": null,
            "description": "",
            "geometryType": "rectangle",
            "labelerLogin": "inbox@datasetninja.com",
            "createdAt": "2024-03-05T11:48:03.459Z",
            "updatedAt": "2024-03-05T11:48:03.459Z",
            "tags": [
                {
                    "id": 109848504,
                    "tagId": 31790,
                    "name": "target id",
                    "value": 72,
                    "labelerLogin": "inbox@datasetninja.com",
                    "createdAt": "2024-03-05T11:48:03.459Z",
                    "updatedAt": "2024-03-05T11:48:03.459Z"
                },
                {
                    "id": 109848505,
                    "tagId": 31791,
                    "name": "no out",
                    "value": null,
                    "labelerLogin": "inbox@datasetninja.com",
                    "createdAt": "2024-03-05T11:48:03.459Z",
                    "updatedAt": "2024-03-05T11:48:03.459Z"
                },
                {
                    "id": 109848506,
                    "tagId": 31794,
                    "name": "no occlusion",
                    "value": null,
                    "labelerLogin": "inbox@datasetninja.com",
                    "createdAt": "2024-03-05T11:48:03.459Z",
                    "updatedAt": "2024-03-05T11:48:03.459Z"
                }
            ],
            "classTitle": "car",
            "points": {
                "exterior": [
                    [
                        794,
                        205
                    ],
                    [
                        848,
                        232
                    ]
                ],
                "interior": []
            }
        },
        {
            "id": 151311397,
            "classId": 6544594,
            "objectId": null,
            "description": "",
            "geometryType": "rectangle",
            "labelerLogin": "inbox@datasetninja.com",
            "createdAt": "2024-03-05T11:48:03.460Z",
            "updatedAt": "2024-03-05T11:48:03.460Z",
            "tags": [
                {
                    "id": 109848507,
                    "tagId": 31790,
                    "name": "target id",
                    "value": 73,
                    "labelerLogin": "inbox@datasetninja.com",
                    "createdAt": "2024-03-05T11:48:03.460Z",
                    "updatedAt": "2024-03-05T11:48:03.460Z"
                },
                {
                    "id": 109848508,
                    "tagId": 31791,
                    "name": "no out",
                    "value": null,
                    "labelerLogin": "inbox@datasetninja.com",
                    "createdAt": "2024-03-05T11:48:03.460Z",
                    "updatedAt": "2024-03-05T11:48:03.460Z"
                },
                {
                    "id": 109848509,
                    "tagId": 31794,
                    "name": "no occlusion",
                    "value": null,
                    "labelerLogin": "inbox@datasetninja.com",
                    "createdAt": "2024-03-05T11:48:03.460Z",
                    "updatedAt": "2024-03-05T11:48:03.460Z"
                }
            ],
            "classTitle": "car",
            "points": {
                "exterior": [
                    [
                        826,
                        173
                    ],
                    [
                        880,
                        199
                    ]
                ],
                "interior": []
            }
        },
        {
            "id": 151311398,
            "classId": 6544594,
            "objectId": null,
            "description": "",
            "geometryType": "rectangle",
            "labelerLogin": "inbox@datasetninja.com",
            "createdAt": "2024-03-05T11:48:03.460Z",
            "updatedAt": "2024-03-05T11:48:03.460Z",
            "tags": [
                {
                    "id": 109848510,
                    "tagId": 31790,
                    "name": "target id",
                    "value": 74,
                    "labelerLogin": "inbox@datasetninja.com",
                    "createdAt": "2024-03-05T11:48:03.460Z",
                    "updatedAt": "2024-03-05T11:48:03.460Z"
                },
                {
                    "id": 109848511,
                    "tagId": 31791,
                    "name": "no out",
                    "value": null,
                    "labelerLogin": "inbox@datasetninja.com",
                    "createdAt": "2024-03-05T11:48:03.460Z",
                    "updatedAt": "2024-03-05T11:48:03.460Z"
                },
                {
                    "id": 109848512,
                    "tagId": 31794,
                    "name": "no occlusion",
                    "value": null,
                    "labelerLogin": "inbox@datasetninja.com",
                    "createdAt": "2024-03-05T11:48:03.460Z",
                    "updatedAt": "2024-03-05T11:48:03.460Z"
                }
            ],
            "classTitle": "car",
            "points": {
                "exterior": [
                    [
                        910,
                        158
                    ],
                    [
                        963,
                        182
                    ]
                ],
                "interior": []
            }
        },
        {
            "id": 151311399,
            "classId": 6544594,
            "objectId": null,
            "description": "",
            "geometryType": "rectangle",
            "labelerLogin": "inbox@datasetninja.com",
            "createdAt": "2024-03-05T11:48:03.461Z",
            "updatedAt": "2024-03-05T11:48:03.461Z",
            "tags": [
                {
                    "id": 109848513,
                    "tagId": 31790,
                    "name": "target id",
                    "value": 75,
                    "labelerLogin": "inbox@datasetninja.com",
                    "createdAt": "2024-03-05T11:48:03.461Z",
                    "updatedAt": "2024-03-05T11:48:03.461Z"
                },
                {
                    "id": 109848514,
                    "tagId": 31792,
                    "name": "medium out",
                    "value": null,
                    "labelerLogin": "inbox@datasetninja.com",
                    "createdAt": "2024-03-05T11:48:03.461Z",
                    "updatedAt": "2024-03-05T11:48:03.461Z"
                },
                {
                    "id": 109848515,
                    "tagId": 31794,
                    "name": "no occlusion",
                    "value": null,
                    "labelerLogin": "inbox@datasetninja.com",
                    "createdAt": "2024-03-05T11:48:03.461Z",
                    "updatedAt": "2024-03-05T11:48:03.461Z"
                }
            ],
            "classTitle": "car",
            "points": {
                "exterior": [
                    [
                        988,
                        143
                    ],
                    [
                        1022,
                        165
                    ]
                ],
                "interior": []
            }
        }
    ]
}